google_oauth2l-1.0.2.dist-info/DESCRIPTION.rst
google_oauth2l-1.0.2.dist-info/METADATA
google_oauth2l-1.0.2.dist-info/RECORD
google_oauth2l-1.0.2.dist-info/WHEEL
google_oauth2l-1.0.2.dist-info/entry_points.txt
google_oauth2l-1.0.2.dist-info/metadata.json
google_oauth2l-1.0.2.dist-info/top_level.txt
oauth2l/__init__.py
oauth2l/oauth2l_test.py
