Metadata-Version: 1.1
Name: google-oauth2l
Version: 1.0.2
Summary: command-line google oauth tools
Home-page: http://github.com/google/oauth2l
Author: Craig Citro
Author-email: craigcitro@google.com
License: Apache 2.0
Keywords: apitools
Platform: UNKNOWN
Classifier: License :: OSI Approved :: Apache Software License
Classifier: Programming Language :: Python :: 2
Classifier: Programming Language :: Python :: 2.7
Classifier: Programming Language :: Python :: 3
Classifier: Programming Language :: Python :: 3.5
Classifier: Topic :: Software Development :: Libraries
Classifier: Topic :: Software Development :: Libraries :: Python Modules
